pylogger_unified/__init__.py
pylogger_unified/logger.py
pylogger_unified-0.0.2.dist-info/METADATA
pylogger_unified-0.0.2.dist-info/WHEEL
pylogger_unified-0.0.2.dist-info/licenses/LICENSE
pylogger_unified-0.0.2.dist-info/RECORD
