Metadata-Version: 2.1
Name: pylogger_unified
Version: 0.0.2
Summary: A python wrapper that handles web logging, standard application logging to different format: json (gelf), colored text, raw, gnome notifications
Project-URL: Homepage, https://github.com/JayBeeDe/pylogger_unified
Project-URL: Bug Tracker, https://github.com/JayBeeDe/pylogger_unified/issues
Author: JayBeeDe
License-File: LICENSE
Classifier: License :: OSI Approved :: GNU General Public License v3 (GPLv3)
Classifier: Operating System :: OS Independent
Classifier: Programming Language :: Python :: 3
Requires-Python: >=3.7
Requires-Dist: python-json-logger>=2.0.4
